llacie/__init__.py
llacie/app.py
llacie/config.py
llacie/db.py
llacie/edw.py
llacie/evaluate.py
llacie/text_wrangling.py
llacie/utils.py
llacie/vocab.py
llacie/batch/__init__.py
llacie/batch/apptainer_slurm.py
llacie/batch/bsub.py
llacie/batch/kube_slurm.py
llacie/batch/slurm.py
llacie/batch/sh/apptainer_slurm.sh
llacie/batch/sh/kube_slurm.sh
llacie/cache/__init__.py
llacie/cache/abstract.py
llacie/cache/sqlite.py
llacie/etc/odbcinst.ini
llacie/grammars/json_arr.gbnf
llacie/grammars/json_arr_of_strings.gbnf
llacie/inference/__init__.py
llacie/inference/llama_cpp.py
llacie/inference/llama_cpp_python.py
llacie/inference/vllm.py
llacie/scripts/__init__.py
llacie/scripts/llacie.py
llacie/sql/episodes.sql
llacie/sql/schema.sql
llacie/strategies/__init__.py
llacie/strategies/abstract.py
llacie/strategies/abstract_llama_cpp.py
llacie/strategies/abstract_vllm.py
llacie/strategies/abstract_vllm_or_lcp.py
llacie/strategies/episode_label/__init__.py
llacie/strategies/episode_label/pres_sx_eplab1/__init__.py
llacie/strategies/episode_label/pres_sx_eplab1/llama1.py
llacie/strategies/episode_label/pres_sx_eplab2/__init__.py
llacie/strategies/episode_label/pres_sx_eplab2/llama31_8b.py
llacie/strategies/episode_label/pres_sx_eplab2/llama3_8b.py
llacie/strategies/episode_label/pres_sx_eplab2/llama3_8b_byterm.py
llacie/strategies/episode_label/pres_sx_eplab2_top30/__init__.py
llacie/strategies/episode_label/pres_sx_eplab2_top30/llama3_8b.py
llacie/strategies/feature/__init__.py
llacie/strategies/feature/presenting_sx/__init__.py
llacie/strategies/feature/presenting_sx/llama1.py
llacie/strategies/feature/presenting_sx/llama31_8b.py
llacie/strategies/feature/presenting_sx/llama3_8b.py
llacie/strategies/feature/presenting_sx/llama3_8b_byterm.py
llacie/strategies/section/__init__.py
llacie/strategies/section/hpi_short/__init__.py
llacie/strategies/section/hpi_short/regex.py
llacie/tasks/__init__.py
llacie/tasks/abstract.py
llacie/tasks/episode_label.py
llacie/tasks/feature.py
llacie-1.0.4.dist-info/entry_points.txt
llacie-1.0.4.dist-info/licenses/LICENSE
llacie-1.0.4.dist-info/WHEEL
llacie-1.0.4.dist-info/METADATA
llacie-1.0.4.dist-info/RECORD
