Metadata-Version: 2.4
Name: llacie
Version: 1.0.4
Summary: An LLM-based clinical information extraction toolkit.
Keywords: natural language processing,large language model,clinical informatics
Author-email: Theodore Pak <theodore.r.pak@gmail.com>
Requires-Python: >= 3.11
Classifier: Programming Language :: Python :: 3.11
Classifier: Programming Language :: Python :: 3.12
Classifier: Programming Language :: Python :: 3.13
Classifier: Programming Language :: Python :: 3.14
License-File: LICENSE
Requires-Dist: click
Requires-Dist: python-dotenv
Requires-Dist: sqlalchemy
Requires-Dist: psycopg2
Requires-Dist: pandas
Requires-Dist: openpyxl
Requires-Dist: platformdirs
Requires-Dist: tqdm
Requires-Dist: sentencepiece
Requires-Dist: protobuf
Requires-Dist: transformers
Requires-Dist: scikit-learn
Requires-Dist: jinja2
Requires-Dist: tabulate
Requires-Dist: confidenceinterval
Requires-Dist: llama-cpp-python==0.3.2
Requires-Dist: flit ; extra == "dev"
Requires-Dist: pyodbc ; extra == "edw"
Requires-Dist: pytest>=7.0 ; extra == "test"
Requires-Dist: pytest-cov>=4.0 ; extra == "test"
Requires-Dist: pytest-timeout>=2.1 ; extra == "test"
Requires-Dist: pytest-dependency>=0.5.1 ; extra == "test"
Provides-Extra: dev
Provides-Extra: edw
Provides-Extra: test
